{"usersPremissions": [{"userID": "63ac46f06e8bd447db5499e9", "premissions": ["View Subscriptions", "Create Subscriptions", "Update Subscriptions", "Delete Subscriptions", "View Movies", "Create Movies", "Update Movies", "Delete Movies"]}, {"premissions": ["View Subscriptions"], "userID": "63b684e5b5526b1476e9fea4"}, {"premissions": ["View Subscriptions", "Update Subscriptions", "Delete Subscriptions", "View Movies"], "userID": "63b6a2acb4022cdf2b10e384"}, {"premissions": ["View Subscriptions"], "userID": "63beee59d326178b3ffb7e77"}, {"premissions": ["View Subscriptions", "Update Subscriptions"], "userID": "63c7e9753774e815444c47c7"}, {"premissions": ["View Movies", "Update Movies", "Delete Movies"], "userID": "63cecf6efafe67885b06780c"}]}